diagify/__init__.py
diagify/cli.py
diagify/diagram_executor.py
diagify/llm_client.py
diagify/main.py
diagify/system_prompt.py
diagify/utils.py
diagify/validation.py
diagify-0.1.4.dist-info/METADATA
diagify-0.1.4.dist-info/WHEEL
diagify-0.1.4.dist-info/entry_points.txt
diagify-0.1.4.dist-info/top_level.txt
diagify-0.1.4.dist-info/RECORD
